README.md
setup.py
simpledb_dev2.egg-info/PKG-INFO
simpledb_dev2.egg-info/SOURCES.txt
simpledb_dev2.egg-info/dependency_links.txt
simpledb_dev2.egg-info/entry_points.txt
simpledb_dev2.egg-info/not-zip-safe
simpledb_dev2.egg-info/requires.txt
simpledb_dev2.egg-info/top_level.txt
simpledbdev2/__init__.py
simpledbdev2/__main__.py
simpledbdev2/config.py
simpledbdev2/portalocker.py
simpledbdev2/simpledb_dev.py
simpledbdev2/templates/__init__.py
simpledbdev2/tests/__init__.py