Metadata-Version: 1.1
Name: simpledb-dev2
Version: 0.1
Summary: A local SimpleDB server
Home-page: https://github.com/rcook/simpledb-dev2
Author: Matthew Painter and others
Author-email: rcook@rcook.org
License: GNU GPL v3
Platform: UNKNOWN
Classifier: Development Status :: 3 - Alpha
Classifier: License :: OSI Approved :: GNU General Public License v3 (GPLv3)
Classifier: Programming Language :: Python :: 2.7
